streamlit_launcher/__init__.py
streamlit_launcher/ai.jpg
streamlit_launcher/cli.py
streamlit_launcher/dashboard.py
streamlit_launcher/gambar.ico
streamlit_launcher/gambar.jpg
streamlit_launcher/gambar2.jpg
streamlit_launcher/gambar3.jpg
streamlit_launcher/gui.py
streamlit_launcher-4.0.1.dist-info/licenses/LICENSE
streamlit_launcher-4.0.1.dist-info/licenses/license.txt
streamlit_launcher-4.0.1.dist-info/METADATA
streamlit_launcher-4.0.1.dist-info/WHEEL
streamlit_launcher-4.0.1.dist-info/entry_points.txt
streamlit_launcher-4.0.1.dist-info/top_level.txt
streamlit_launcher-4.0.1.dist-info/RECORD
