Metadata-Version: 2.4
Name: streamlit_launcher
Version: 4.0.1
Summary: Streamlit Launcher is an advanced no-code platform that integrates Streamlit, deep learning, and machine learning into one unified environment. It allows users to train models, visualize data, and perform complete statistical and analytical tasks effortlessly without writing any code. With powerful AI-driven automation, it simplifies complex workflows for research, health, and data science.
Home-page: https://github.com/royhtml
Author: Dwi Bakti N Dev
Author-email: dwibakti76@gmail.com
Project-URL: Profile, https://profiledwibaktindev.netlify.app/
Project-URL: Itch.io, https://royhtml.itch.io/
Project-URL: Facebook, https://www.facebook.com/Royhtml
Project-URL: Webtoons, https://www.webtoons.com/id/canvas/mariadb-hari-senin/episode-4-coding-championship/viewer?title_no=1065164&episode_no=4
Project-URL: Global Komik, https://globalcomix.com/read/dc7f0116-7187-49a0-a27b-62b6c81eb435/1?utm_medium=GCMobileReaderApp&utm_source=share-release&utm_campaign=Royy&utm_term=122186
Project-URL: Portfolio, https://portofolio-dwi-bakti-n-dev-liard.vercel.app/
Project-URL: Download, https://pepy.tech/projects/streamlit-launcher?timeRange=threeMonths&category=version&includeCIDownloads=true&granularity=daily&viewType=line&versions=3.8.7%2C3.8.5%2C3.7.9
Classifier: Programming Language :: Python :: 3
Classifier: Topic :: Scientific/Engineering :: Artificial Intelligence
Classifier: Topic :: Scientific/Engineering :: Information Analysis
Classifier: Topic :: Scientific/Engineering :: Medical Science Apps.
Classifier: Topic :: Software Development :: User Interfaces
Classifier: Topic :: Scientific/Engineering :: Visualization
Classifier: Topic :: Software Development :: Build Tools
Classifier: License :: OSI Approved :: MIT License
Classifier: Operating System :: OS Independent
Classifier: Intended Audience :: Developers
Classifier: Intended Audience :: Science/Research
Classifier: Intended Audience :: Healthcare Industry
Classifier: Intended Audience :: Education
Classifier: Operating System :: OS Independent
Classifier: Operating System :: Microsoft :: Windows
Classifier: Operating System :: POSIX :: Linux
Requires-Python: >=3.7
License-File: LICENSE
License-File: license.txt
Requires-Dist: pillow<11.0,>=8.0
Requires-Dist: pyinstaller<7.0,>=4.0
Requires-Dist: pyqt5<6.0,>=5.15
Requires-Dist: streamlit<2.0,>=1.0
Requires-Dist: numpy<2.0,>=1.21
Requires-Dist: pandas<3.0,>=1.3
Requires-Dist: scikit-learn<2.0,>=1.0
Requires-Dist: matplotlib<4.0,>=3.4
Requires-Dist: seaborn<1.0,>=0.11
Requires-Dist: tensorflow<3.0,>=2.6
Requires-Dist: torch<3.0,>=1.9
Requires-Dist: plotly<7.0,>=5.0
Requires-Dist: openpyxl<4.0,>=3.0
Requires-Dist: scipy<2.0,>=1.7
Requires-Dist: joblib<2.0,>=1.1
Requires-Dist: requests<3.0,>=2.25
Requires-Dist: opencv-python>=4.5
Requires-Dist: keras>=2.6
Requires-Dist: xgboost>=1.5
Requires-Dist: lightgbm>=3.3
Requires-Dist: catboost>=1.0
Requires-Dist: statsmodels>=0.13
Requires-Dist: networkx>=2.6
Requires-Dist: pyarrow>=5.0
Requires-Dist: sphinx>=4.0
Requires-Dist: sphinx-rtd-theme>=1.0
Requires-Dist: sphinx-autodoc-typehints>=1.0
Requires-Dist: pytest>=6.0
Requires-Dist: pytest-cov>=2.0
Requires-Dist: black>=21.0
Requires-Dist: flake8>=3.9
Requires-Dist: mypy>=0.910
Requires-Dist: pre-commit>=2.0
Dynamic: author
Dynamic: author-email
Dynamic: classifier
Dynamic: description
Dynamic: description-content-type
Dynamic: home-page
Dynamic: license-file
Dynamic: project-url
Dynamic: requires-dist
Dynamic: requires-python
Dynamic: summary
